Metadata-Version: 2.1
Name: masked-convolution
Version: 0.3.0
Summary: A PyTorch wrapper for masked convolutions
Home-page: http://github.com/suflaj/masked-convolution
Author: Miljenko Šuflaj
Author-email: headsouldev@gmail.com
License: Apache License 2.0
Keywords: pytorch torch convolution mask
Platform: UNKNOWN
Classifier: Development Status :: 3 - Alpha
Classifier: Environment :: GPU
Classifier: Intended Audience :: Developers
Classifier: Intended Audience :: Education
Classifier: Intended Audience :: Information Technology
Classifier: Intended Audience :: Science/Research
Classifier: License :: OSI Approved :: Apache Software License
Classifier: Natural Language :: English
Classifier: Operating System :: OS Independent
Classifier: Programming Language :: Python :: 3 :: Only
Classifier: Programming Language :: Python :: 3.8
Classifier: Topic :: Scientific/Engineering :: Artificial Intelligence
Classifier: Topic :: Scientific/Engineering :: Information Analysis
Classifier: Topic :: Scientific/Engineering :: Mathematics
